aevi/__init__.py
aevi/__version__.py
animus/__init__.py
animus/__version__.py
aevi-0.1.dist-info/METADATA
aevi-0.1.dist-info/WHEEL
aevi-0.1.dist-info/top_level.txt
aevi-0.1.dist-info/RECORD
